{
  "animateLoading": true,
  "borderRadius": "{{appsmith.theme.borderRadius.appBorderRadius}}",
  "bottomRow": 24,
  "dynamicBindingPathList": [
    {
      "key": "truncateButtonColor"
    },
    {
      "key": "borderRadius"
    },
    {
      "key": "text"
    }
  ],
  "dynamicHeight": "AUTO_HEIGHT",
  "dynamicTriggerPathList": [],
  "fontFamily": "Montserrat",
  "fontSize": "1rem",
  "fontStyle": "BOLD",
  "isLoading": false,
  "isVisible": true,
  "key": "kiiys4abnx",
  "leftColumn": 31,
  "maxDynamicHeight": 9000,
  "minDynamicHeight": 4,
  "minWidth": 450,
  "mobileBottomRow": 12,
  "mobileLeftColumn": 1,
  "mobileRightColumn": 17,
  "mobileTopRow": 8,
  "needsErrorInfo": false,
  "originalBottomRow": 27,
  "originalTopRow": 16,
  "overflow": "NONE",
  "parentColumnSpace": 14.90625,
  "parentId": "w423tt81l8",
  "parentRowSpace": 10,
  "renderMode": "CANVAS",
  "responsiveBehavior": "fill",
  "rightColumn": 62,
  "shouldTruncate": false,
  "text": "Create Date : {{Table1.triggeredRow.created_at}}\n\nClass Date (If class is Onsite) :\n\n{{Table1.triggeredRow.Date}} {{Table1.triggeredRow.Time}}",
  "textAlign": "LEFT",
  "textColor": "#231F20",
  "topRow": 13,
  "truncateButtonColor": "{{appsmith.theme.colors.primaryColor}}",
  "type": "TEXT_WIDGET",
  "version": 1,
  "widgetId": "re1el4iryy",
  "widgetName": "CourseInfoCopy"
}