{
  "gitSyncId": "67c32501352cc33eef815a97_4a38b640-2fc5-4d73-bf9d-c0554052caf9",
  "id": "Main_CourseFindOnsite",
  "pluginId": "mongo-plugin",
  "pluginType": "DB",
  "unpublishedAction": {
    "actionConfiguration": {
      "encodeParamsToggle": true,
      "formData": {
        "aggregate": {
          "arrayPipelines": {
            "data": ""
          },
          "limit": {
            "data": "10"
          }
        },
        "collection": {
          "data": "onsite_courses"
        },
        "command": {
          "data": "FIND"
        },
        "count": {
          "query": {
            "data": ""
          }
        },
        "delete": {
          "limit": {
            "data": "SINGLE"
          },
          "query": {
            "data": ""
          }
        },
        "distinct": {
          "key": {
            "data": ""
          },
          "query": {
            "data": ""
          }
        },
        "find": {
          "limit": {
            "data": ""
          },
          "projection": {
            "data": "{course_name : 1 , _id : 0}"
          },
          "query": {
            "data": ""
          },
          "skip": {
            "data": ""
          },
          "sort": {
            "data": ""
          }
        },
        "insert": {
          "documents": {
            "data": ""
          }
        },
        "misc": {
          "formToNativeQuery": {
            "data": "{\n  \"find\": \"onsite_courses\",\n  \"limit\": 10,\n  \"batchSize\": 10\n}\n",
            "status": "SUCCESS"
          }
        },
        "smartSubstitution": {
          "data": true
        },
        "updateMany": {
          "limit": {
            "data": "SINGLE"
          },
          "query": {
            "data": ""
          },
          "update": {
            "data": ""
          }
        }
      },
      "paginationType": "NONE",
      "timeoutInMillisecond": 10000
    },
    "confirmBeforeExecute": false,
    "datasource": {
      "id": "benkyou",
      "isAutoGenerated": false,
      "name": "benkyou",
      "pluginId": "mongo-plugin"
    },
    "dynamicBindingPathList": [],
    "executeOnLoad": false,
    "name": "CourseFindOnsite",
    "pageId": "Main",
    "userSetOnLoad": false
  }
}